pyfill-0.1.3.dist-info/METADATA
pyfill-0.1.3.dist-info/WHEEL
pyfill-0.1.3.dist-info/entry_points.txt
pyfill-0.1.3.dist-info/licenses/LICENSE
pyfill/__init__.py
pyfill/datetime.py
pyfill-0.1.3.dist-info/RECORD
