Metadata-Version: 2.1
Name: pyfill
Version: 0.1.3
Summary: pyfill is a tool to detect Python versions and automatically replace deprecated features (e.g. datetime.utcnow) with alternative methods.
Author-Email: AmaseCocoa <cocoa@amase.cc>
License: CC0-1.0
Requires-Python: >=3.9
